dirlog.py
dirlog-1.2.1.dist-info/LICENSE
dirlog-1.2.1.dist-info/METADATA
dirlog-1.2.1.dist-info/WHEEL
dirlog-1.2.1.dist-info/entry_points.txt
dirlog-1.2.1.dist-info/top_level.txt
dirlog-1.2.1.dist-info/RECORD
