Metadata-Version: 2.1
Name: dirlog
Version: 1.2.1
Summary: keep a log of directories you visit to get back fast
Home-page: https://github.com/ninjaaron/dirlog
Author: Aaron Christianson
Author-email: ninjaaron@gmail.com
License: BSD
Platform: UNKNOWN
Classifier: Programming Language :: Python :: 3.5
